{"JID":"TCDV,110,簡上,403,20230825,1","JYEAR":"110","JCASE":"簡上","JNO":"403","JDATE":"20230825","JTITLE":"損害賠償","JFULL":"臺灣臺中地方法院民事判決\r\n110年度簡上字第403號\r\n上  訴  人  魏欣怡  \r\n\r\n\r\n\r\n訴訟代理人  楊偉奇律師                      \r\n被上訴人    劉政鵬  \r\n\r\n訴訟代理人  易佩萱律師\r\n上列當事人間請求損害賠償事件，上訴人對於民國110年8月26日\r\n本院臺中簡易庭110年度簡字第74號第一審判決，提起上訴，並\r\n為訴之擴張，本院合議庭於民國112年7月20日言詞辯論終結，判\r\n決如下：\r\n    主    文\r\n一、原判決關於駁回後開第2項部分之訴及該部分假執行之聲請 \r\n    ，暨訴訟費用（除確定部分外）之裁判均廢棄。\r\n二、上開廢棄部分，被上訴人應再給付上訴人新臺幣肆拾萬壹仟\r\n    壹佰柒拾貳元，及自民國110年5月29日起，至清償日止，按\r\n    週年利率百分之五計算之利息。\r\n三、被上訴人應另給付上訴人新臺幣貳拾捌萬捌仟零伍拾玖元元\r\n    ，及其中新臺幣陸仟貳佰零陸元自民國 110 年10 月 15 日\r\n    起，其餘新臺幣貳拾捌萬壹仟捌佰伍拾參元自民國111年5 \r\n    月24 日起，至清償日止，均按週年利率百分之五計算之利\r\n    息。\r\n四、上訴人其餘上訴及擴張之訴均駁回。\r\n五、第一審（除確定部分外）、第二審訴訟費用（含擴張之訴部\r\n    分）由被上訴人負擔百分之三十二，餘由上訴人負擔。\r\n    事實及理由\r\n甲、程序部分：\r\n    按在第二審為訴之變更或追加，非經他造同意，不得為之，\r\n    但請求之基礎事實同一者；擴張或減縮應受判決事項之聲明\r\n    者，不在此限，此觀諸民事訴訟法第446條第1項、第255條\r\n    第1項第2款、第3款等規定即明。所謂「請求之基礎事實同\r\n    一者」，係指變更或追加之訴與原訴之主要爭點有其共同性\r\n    ，各請求利益之主張在社會生活上可認為同一或關連，而就\r\n    原請求之訴訟及證據資料，於審理繼續進行在相當程度範圍\r\n    內具有同一性或一體性，得期待於後請求之審理予以利用，\r\n    俾先後兩請求在同一程序得加以解決，避免重複審理，進而\r\n    為統一解決紛爭者即屬之(最高法院100年度台抗字第716號\r\n    裁判意旨參照)。上訴人於原審聲明為：被上訴人應給付上\r\n    訴人新臺幣(下同)970,577 元，及自起訴狀繕本送達翌日起\r\n    至清償日止，按週年利率百分之五計算之利息。經原審為部\r\n    分勝訴，上訴人就敗訴部分，提起上訴，最終聲明如後所示\r\n    ，核屬聲明之擴張，且上訴人擴張之部分與原訴之基礎事實\r\n    均基於兩造間侵權行為之糾紛，彼此互具共同性，在社會生\r\n    活上可認為同一或關連，且原請求之訴訟及證據資料，於擴\r\n    張部分審理中得加以利用，自屬請求之基礎事實同一，應予\r\n    准許，合先陳明。\r\n乙、實體部分：\r\n壹、上訴人主張部分：\r\n一、於原審主張：\r\n  ㈠被上訴人於民國108 年9 月6 日8 時22分許，騎乘車牌號碼0\r\n    00-000 號普通重型機車，沿臺中市西屯區黎明路3段由東往\r\n    西方向行駛，行經該路段與僑光路交岔路口前，以當時天候\r\n    晴、日間自然光線、柏油路面乾燥、無缺陷及障礙物、視距\r\n    良好的客觀狀況來看，客觀上並沒有使被上訴人無法注意行\r\n    車安全的情形下，其卻疏未依規定注意車前狀況，隨時保持\r\n    必要之應變措施，結果因煞車不及而追撞前方等停紅燈由上\r\n    訴人所騎乘車牌號碼000-000 號普通重型機車車尾，致上訴\r\n    人人車倒地後，受有右側膝部擦挫傷及双肩挫傷、頸椎第三\r\n    /四節椎間盤突出及頸椎揮鞭式損傷等傷害。上訴人自本件\r\n    車禍後，經常出現血壓、心跳無法調節的現象，經醫師檢查\r\n    後，診斷患有自主神經功能異常，主因係車禍後頸椎揮鞭式\r\n    損傷。且視力亦有逐漸模糊之現象，已影響上訴人日常開車\r\n    行為。\r\n  ㈡上訴人因上述傷勢，因而支出醫療費用340,265元、就診支出\r\n    之交通費用53,900元、購買醫療物品1,465元，另因自主神\r\n    經功能異常及視力模糊問題，需至門診治療，預估1個月需\r\n    花費1,000元，為期3年而需支出醫療費用36,000元。另受有\r\n    勞動能力減損之損害277,603元、心理諮商費用6,000元等損\r\n    害。上訴人因上述傷勢而精神痛苦，故一併請求慰撫金25萬\r\n    元，故依民法第184條第1項前段、第2項、第191條之2、第1\r\n    93條第1項、第195條第1項規定，提起本件訴訟等語，並聲\r\n    明：1.被上訴人應給付上訴人970,577元，及自起訴狀繕本\r\n    送達翌日起至清償日止，按週年利率百分之五計算之利息。\r\n    2.願供擔保，請准宣告假執行。\r\n二、於上訴補稱：\r\n  ㈠上訴人於事故遭撞擊時，人車向右倒地，力道非輕，所受傷\r\n    勢絕非僅有右側膝部，斯時已有感覺上肢無法正常使力將機\r\n    車立起，便請求被上訴人協助扶機車，之後即前往福雅骨科\r\n    家庭醫學科診所（下簡稱福雅診所），接受門診包紮膝部外\r\n    傷。而當時因上訴人未能察覺上肢傷痛異樣，無併向醫生說\r\n    明。然事故當晚，上訴人即感到身體右側上肢異常疼痛，當\r\n    下遂以LINE通知被上訴人，被上訴人亦回覆知悉。隔日即10\r\n    8年9月7日及108年9 月9 日，上訴人再前往同診所復健治療\r\n    ，因無改善，於108年9 月9 日隨即前往同春堂內科傷科中\r\n    醫診所（下稱同春堂診所）治療上開傷勢，但仍未獲改善，\r\n    108年9月10日再前往以馬內利復健科神經科診所（下稱以馬\r\n    內利診所）檢查後，確認受有「兩側肩部挫傷、頸椎揮鞭式\r\n    損傷」，上訴人在前開期間均有透過LINE與被上訴人聯繫告\r\n    知傷勢狀況，被上訴人後續亦有數度詢問上訴人手腳傷勢情\r\n    形。「頸椎揮鞭式損傷」在臨床上通常不會立刻顯現症狀，\r\n    而是受傷後1-5天才會逐漸發生，亦經臺灣大學醫學院附設\r\n    醫院雲林分院（下稱臺大醫院雲林分院）鑑定確認上訴人傷\r\n    勢乃後車追撞造成，屬頸椎揮鞭式損傷典型之受傷機轉，且\r\n    為損傷後之變化而非退化性變化。上訴人並無過度運動負荷\r\n    造成二次傷害，更無與有過失、遲延上訴人自己身體復原進\r\n    度之情形。\r\n  ㈡醫療費用：\r\n　1.於原審請求但未獲判賠之醫療費（如附表一所示）：同春堂\r\n    內科傷科中醫診所（下稱同春堂診所）18,820元、臺中榮民\r\n    總醫院12,685元、以馬內利診所225,260元、中科學善物理\r\n    治療所12,900元、永康聯合中醫診所（下稱永康中醫診所）\r\n    15,890元，共計285,555元。\r\n　2.於二審擴張醫療費（如附表二所示所示）：上訴人持續支出\r\n    必要之醫療費用，含臺中榮民總醫院4,566元、以馬內利診\r\n    所81,690元、永康中醫診所1,670元，共計87,926元。　　\r\n  ㈢勞動能力減損：\r\n　1.於原審請求但未獲判賠之勞動能力減損：277,603元。\r\n　2.於二審擴張請求勞動能力減損：應以上訴人受傷前與受傷後\r\n    身體健康狀況，衡量勞動能力減損所受補償之金額，非必然\r\n    以上訴人薪資是否減低為根據。上訴人因本事故受傷時為31\r\n    歲，勞動能力減損比例為10%，上訴人計算至65歲退休日止\r\n    ，尚有34年，每月薪資38,750元、年收入為547,411元，依\r\n    霍夫曼式計算法扣除中間利息，上訴人勞動能力減損金額為\r\n    1,104,864元，經扣除原審請求但未獲判賠之勞動能力減損2\r\n    77,603元，為827,261元。\r\n  ㈣精神慰撫金：\r\n　1.於原審請求但未獲判賠之精神慰撫金：225,000元。\r\n　2.於二審擴張請求之精神慰撫金：595,136元。　　\r\n　㈤綜上，於原審請求但未獲判賠之部分，被上訴人應再給付上\r\n    訴人647,232元（醫療費285,555元+勞動能力減損277,603元\r\n    +精神慰撫金225,000元-已給付強制責任險140,926元=647,2\r\n    32元）。於二審擴張請求之部分，被上訴人應另給付上訴人\r\n    1,510,323元（醫療費87,926元+勞動能力減損827,261元+精\r\n    神慰撫金595,136元=1,510,323元）。　　　\r\n貳、被上訴人抗辯部分：\r\n一、被上訴人於原審抗辯：對於上訴人因右側膝部挫傷而支出之\r\n    醫療費用970元不爭執，至上訴人主張之其餘傷勢，無從證\r\n    明與系爭車禍有關，上訴人主張因上開傷勢而受有之損害，\r\n    與本件車禍間並無相當因果關係，又上訴人請求之慰撫金數\r\n    額亦過高。縱認上訴人其他傷勢與系爭車禍有關，然上訴人\r\n    於醫囑休養期間從事諸如實彈射擊、路跑、射箭、極限戰鬥\r\n    拳及加強背部、肩部肌肉訓練、跳躍及斜坡衝刺跑步之活動\r\n    ，進而影響或遲延其身體復原進程，顯見其就損害之擴大與\r\n    有過失等語，資為抗辯，並聲明：1.上訴人之訴及假執行之\r\n    聲請均駁回。2.如受不利判決，願供擔保，請准宣告免為假\r\n    執行。\r\n二、於上訴補稱：　　　　　　　　　　\r\n  ㈠上訴人於108年9月6日車禍當日及同年月7日、9日、28日、10\r\n    月1日、4日前往福雅診所接受門診、復健治療，該院於108\r\n    年11月14日所出具之診斷證明書上僅記載上訴人受有「右側\r\n    膝部擦挫傷」，並未提及上訴人受有其他傷勢。若上訴人於\r\n    車禍時確受有其他傷勢，在其曾於108年9月7日、9日已數次\r\n    就診，卻未在該院針對其餘傷勢進行診斷、治療，而是拖到\r\n    4天後之9月10日才前往以馬內利診所治療，並診斷其傷勢為\r\n    「兩側肩部挫傷」，則上開傷勢是否確因車禍所致，即有可\r\n    疑。而觀諸上訴人於108年9月10日至以馬內利診所進行復健\r\n    5次，另於109年2月21日、3月3日至臺中榮民醫院診療，嗣\r\n    經該院復健科110年6月11日鑑定書載明「原告受傷至今已近\r\n    兩年，目前仍有頭痛、頸部疼痛、兩肩疼痛等症狀」、「原\r\n    告頸椎及雙肩受傷導致疼痛，操控機車可能有危險，因此傷\r\n    後三個月內不宜騎機車。但期限可能因症狀持續而需延長，\r\n    應由臨床主治醫師判斷；健保規定頸部及扭挫傷之復健黃金\r\n    期為三個月。但實際時間應視當事人恢復情形由臨床主治醫\r\n    師決定，不宜限制亦無法預測。目前當事人仍持續至診所復\r\n    健治療中。」等語，足見上訴人在前述醫囑休養期間不宜騎\r\n    機車、從事原審所臚列之活動，進而影響或遲延上訴人身體\r\n    復原進程，上訴人就損害之擴大與有過失。\r\n　㈡醫療費用：\r\n　1.同春堂診所部分全部剔除：依上訴人所提收據、診斷證明書\r\n    載為：胃及十二指腸疾病、消化系統疾病、身體病況引起的\r\n    失眠症、慢性鼻咽炎、支氣管炎等，顯與本案車禍受傷無關\r\n    ，應予剔除，縱有此部分費用之支出，難認係醫療上所必要\r\n    。⒉\r\n　2.臺中榮民醫院部分全部剔除：上訴人於109年1月7日始至臺\r\n    中榮民醫院求診，距離事故發生時已隔4個月之久，縱此部\r\n    分有因果關係，惟上訴人自108年9月10日起，即於以馬內利\r\n    診所進行復健迄至109年10月16日止、108年12月24日起自宜\r\n    葆傳統整復推拿進行復健迄至109年10月23日止、109年1月1\r\n    8日起自中科學善物理治療所進行復健迄至109年3月16日止\r\n    ，上訴人於108年12月24日起至109年10月16日止，就診療項\r\n    目復健有重覆檢查之虞，應無必要需剔除。\r\n  3.以馬內利診所於108年12月6日以後之費用應剔除：上訴人於\r\n    108年9月10日始至以馬內利診所求診，距離事故發生時已隔\r\n    4天，顯然與此次事故並無關聯，且上訴人於右側膝部擦挫\r\n    傷部分，於求診時並未告知福雅診所醫師，足見該次治療已\r\n    有成效，又縱此部分上訴人已就因果關係為舉證，則就診療\r\n    項目復健仍有重覆檢查之虞，應無必要需剔除。\r\n　4.中科學善物理治療所部分全部剔除：上訴人於108年9月10日\r\n    至以馬內利診所進行復健，是再至中科學善物理治療所進行\r\n    復健部分已有重覆檢查之虞，應予剔除。⒌\r\n　5.永康中醫診所部分全部剔除：上訴人於109年2月27日始至永\r\n    康中醫診所求診，與事故發生時已隔5個月之久，顯然與此\r\n    次事故並無關聯，縱此部分有因果關係，上訴人所提109年2\r\n    月29日（3月4日可再拿藥）、3月5日（3月9日才可再拿藥）\r\n    、6月9日健保處方暨收據，載明適用症睡眠疾患或未載任何\r\n    事項及其相對應之收據，與本案車禍並無關聯，應予剔除。\r\n　㈢勞動能力減損：上訴人111年1月薪資為40,360元，與上訴人\r\n    於原審所提108年9月薪資為38,750元，顯有提升，上訴人於\r\n    系爭車禍事故發生前後月薪是否有減少，應斟酌其所受傷害\r\n    與其職業、智能、性向、年齡、教育等因素加以調整。\r\n　㈣精神慰撫金：上訴人因系爭車禍所受之傷害為右側膝部擦挫\r\n    傷，並非難治或不能復原之傷害，被上訴人有配偶及未成年\r\n    子女待扶養，於車禍發生後積極處理，坦承錯誤，希望與上\r\n    訴人和解，僅因雙方差異過大無法成立，爰請求予以酌減。\r\n貳、本件原審判命被上訴人給付上訴人27,435元，及自109年7月\r\n    16日起至清償日止，按週年利率百分之五計算之利息，及此\r\n    部分准予假執行之宣告，另駁回上訴人逾此範圍之請求。上\r\n    訴人就其敗訴部分，除確定部分外，部分聲明不服，提起上\r\n    訴，並擴張其請求，且於本院上訴聲明：1.原判決關於駁回\r\n    後開第2項部分之訴，及該部分假執行之宣告，暨訴訟費用\r\n    （除確定部分外）之裁判均廢棄。2.被上訴人應再給付上訴\r\n    人647,232元，及自110年5月29日起至清償日止，按週年利\r\n    率百分之五計算之利息。3.被上訴人應另給付上訴人1,510,\r\n    323元，及其中87,926元自聲明上訴狀繕本送達翌日（即 11\r\n    0 年10 月 15日）起，其餘1,422,397元自民事擴張聲明暨\r\n    準備（三）狀繕本送達翌日（即111 5 月24 日）起，均按\r\n    週年利率百分之五計算之利息。4.第一審（除確定部分外）\r\n    、第二審（含擴張之訴部分）訴訟費用，由被上訴人負擔。\r\n    5.願供擔保，請准宣告假執行。被上訴人則答辯聲明：1.上\r\n    訴及擴張之訴與假執行之聲請均駁回。2.訴訟費用（含擴張\r\n    之訴部分）由上訴人負擔。3.如受不利判決，願供擔保請准\r\n    宣告免為假執行。\r\n參、兩造經協商簡化爭點，就下列事項不為爭執，本院自得採為\r\n    判斷之基礎：\r\n一、被上訴人於108 年9 月6 日上午，騎乘車牌號碼000-000 號\r\n    普通重型機車，沿臺中市西屯區黎明路3 段由東往西方向行\r\n    駛，於同日8 時22分許，行至臺中市西屯區黎明3 段與僑光\r\n    路交岔路口前，本應注意車前狀況，隨時保持必要之應變措\r\n    施，而依當時天候晴、日間自然光線、柏油路面乾燥、無缺\r\n    陷及障礙物，視距良好等情，並無不能注意之情事，竟疏未\r\n    注意及此，被上訴人因煞車不及，所騎乘機車頭碰撞前方上\r\n    訴人所騎乘車牌號碼000-000 號普通重型機車車尾，致上訴\r\n    人人車倒地後，受有傷害。\r\n二、上訴人因右側膝部擦挫傷之傷害而至福雅診所就診支出醫療\r\n    費用970 元及購買醫療物品1,465 元，共計2,435 元。\r\n三、被上訴人就本件車禍所涉刑事案件部分，業經臺灣臺中地方\r\n    法院109 年度中交簡字第1661號刑事判決確定，判處被上訴\r\n    人犯過失傷害罪，處拘役40日，如易科罰金，以1,000 元折\r\n    算壹日。\r\n肆、本院之判斷：\r\n一、被上訴人主張因上訴人違規駕駛發生系爭車禍，而受有系爭\r\n    傷害之事實，為上訴人所不爭執（見不爭執事項一）。被上\r\n    訴人致上訴人受傷之上開犯行，業經本院109年度中交簡字\r\n    第1661號刑事判決判處傷害罪，處拘役40日確定，而同此認\r\n    定，亦據本院調閱上開刑事偵審卷宗查核屬實，堪信真實。\r\n二、上訴人因系爭車禍除受有「右側膝部」傷勢外，亦受有双肩\r\n    挫傷、頸椎第三/四節椎間盤突出及頸椎揮鞭式損傷部分：\r\n    上訴人主張其因系爭車禍除受有「右側膝部」傷勢外，亦受\r\n    有双肩挫傷、頸椎第三/四節椎間盤突出及頸椎揮鞭式損傷\r\n    ，固為被上訴人所否認，惟查：\r\n　㈠本件車禍發生當時，上訴人係騎乘機車停等於機車停等區於\r\n    毫無防備之情況下，突遭後方車輛即被上訴人所騎乘之機車\r\n    ，因煞車不及，自後方撞擊上訴人之機車車尾，致上訴人瞬\r\n    間人車倒地並受有身體傷害，此依上訴人機車後方擋泥板遭\r\n    撞擊後留有明顯撞擊痕跡觀之，足認車禍當時撞擊之力道非\r\n    輕，此有上訴人原審所提現場事故照片供參(參原審卷一第 \r\n    85 頁)。又上訴人於事後前往福雅診所雖包紮膝部外傷，然\r\n    於肇事之當晚，上訴人因查覺身體右側上肢異常疼痛之傷情\r\n    ，乃以LINE傳送:「2019/09/06(週五) 23:38 wei :跟你報\r\n    備一下，我剛剛躺下後發現右手臂很痛，無法像左手抬的高\r\n    ，先跟你說一下，我會去做復健。」之訊息通知被上訴人，\r\n    而被上訴人亦回覆:「2019/09/07(週六) 24:16劉=鵬:嗯好\r\n    」，隔日並曾詢問:「2019/09/07 (週六)19:35劉=鵬:魏小\r\n    姐手跟腳有比較好嗎」等語，後續亦有數度詢問上訴人手、\r\n    腳之傷勢情形，此有兩造108年9月6日至109年7月2日LINE對\r\n    話紀錄(見原審卷一第95-102頁、本院卷第149-156 頁），\r\n    及108年9月6日事發當晚之LINE截圖（見本院卷第157頁），\r\n    顯見上訴人主張 於肇事後發現其因車禍除前述而有「右側\r\n    膝部」傷勢外，另有其他不適之症狀，並立即告知被上訴人\r\n    之事實，應屬可採 。\r\n　㈡上訴人主張其於事故發生之當日即108年9月6日前往福雅診所\r\n    ，於108年9月7日、108年9月9日前往福雅診所復健，但未見\r\n    改善，方於108年9月9日再前往同春堂診所求診治療前開上\r\n    肢部位傷勢，然因該上肢部位疼痛情形始終未獲改善，故於\r\n    108年9月10日再另前往以馬內利診所就診，經檢查後，診斷\r\n    確認係受有「兩側肩部挫傷，頸椎揮鞭式損傷」，且其有將\r\n    上情透過LINE通訊軟體與被上訴人聯繫使其知悉所受傷勢之\r\n    情事，除前述LINE對話紀錄外，上訴人復提出同春堂診所之\r\n    109 年2 月15 日診斷證明書、以馬內利診所109年3 月20 \r\n    日診斷證明書（見原審109年度中交簡附民字第77號卷《下簡\r\n    稱附民卷》第25頁、第41頁）在卷可參，按上訴人受傷後，\r\n    對就診事宜，均據實向被上訴人陳明，且有其就診之證明可\r\n    參，實難率以上訴人於108年9月7日及9日前往福雅診所卻未\r\n    在該院針對其餘傷勢進行診斷治療，4天後方前往以馬內利\r\n    診所治療，逕認上訴人所受兩側肩部挫傷等傷勢確非因車禍\r\n    所致。\r\n　㈢且經本院囑託臺大醫院雲林分院鑑定「．．說明㈠依函文所附\r\n    之就醫病歷資料，是否可判斷甲○○所受雙肩挫傷頸椎第三、\r\n    四節椎間盤突出及頸椎揮鞭式損害，確係因其於108年9月6\r\n    日騎乘機車等停紅燈時，遭人騎乘機車煞車不及追撞後車尾\r\n    所導致?」，經鑑定機關以111年8月10日臺大雲分資字第111\r\n    0005342號函覆之鑑定意見:「依函文說明㈠，是。依病歷記\r\n    錄，甲○○之傷勢後車追撞造成，屬頸椎揮鞭式損傷典型之受\r\n    傷機轉。受傷後4日(108年9月10日)之就診記錄即明確表示\r\n    有頸部不適之症狀。後續醫療記錄顯示有慢性頸部痛、頭痛\r\n    、暈眩、睡眠障礙等症狀，前述症狀皆可能於頸椎揮鞭式損\r\n    傷後發生，並可能在經藥物、物理治療後仍形成長期後遺症\r\n    。頸部磁振造影檢查也顯示頸椎第三、四節椎間盤突出等變\r\n    化，應係損傷後之變化而非退化性變化(甲○○受傷時約31歲)\r\n    」等語（見本院卷第411 頁）。鑑定單位已明確肯認上訴人\r\n    所受「雙肩挫傷、頸椎第三/四節椎間盤突出及頸椎揮鞭式\r\n    損害」等傷勢，確係本件交通事故遭被上訴人追撞所致無誤\r\n    ，上訴人之主張應屬有據。\r\n　㈣又上訴人於109年5月8日第一次檢察官開庭偵訊前，即已於10\r\n    9年5月5日提出一份刑事告訴補充理由狀(見本院卷第81-84\r\n    頁），載明上訴人因本件車禍除受有右側膝部擦挫傷外，亦\r\n    受有「兩側肩部挫傷，頸椎揮鞭式損傷」等傷勢，且提出診\r\n    斷證明文件作為告訴補充之證據，惟檢察官未予參酌，刑事\r\n    判決亦未審酌及說明上訴人補充證據有何不予採認之理由，\r\n    自難以刑事判決審認之事實，拘束本院，是被上訴人抗辯刑\r\n    事判決未認定上訴人除前述外傷外，另有其他傷害，上訴人\r\n    主張受傷之範圍不實云云，自無可採。\r\n　㈤基上，上訴人因系爭車禍除受有「右側膝部」傷勢外，亦受\r\n    有双肩挫傷、頸椎第三/四節椎間盤突出及頸椎揮鞭式損傷\r\n    ，應可認定，則上訴人請求被上訴人賠償其所受前述傷害之\r\n    損害，於法有據。\r\n三、因故意或過失，不法侵害他人之權利者，負損害賠償責任；\r\n    汽車、機車或其他非依軌道行駛之動力車輛，在使用中加損\r\n    害於他人者，駕駛人應賠償因此所生之損害；不法侵害他人\r\n    之身體或健康者，對於被害人因此喪失或減少勞動能力或增\r\n    加生活上之需要時，應負損害賠償責任；不法侵害他人之身\r\n    體、健康、名譽、自由、信用、隱私、貞操，或不法侵害其\r\n    他人格法益而情節重大者，被害人雖非財產上之損害，亦得\r\n    請求賠償相當之金額；民法第184 條第1 項前段、第191條\r\n    之2前段、第193 條第1 項、民法第195 條第1 項分別定有\r\n    明文。又當事人已證明受有損害而不能證明其數額或證明顯\r\n    有重大困難者，法院應審酌一切情況，依所得心證定其數額\r\n    。民事訴訟法第222條第2項亦定有明文。被上訴人騎乘普通\r\n    重型機車至事發地點，本應注意車前狀況，隨時保持必要之\r\n    應變措施，而依當時天候晴、日間自然光線、柏油路面乾燥\r\n    、無缺陷及障礙物，視距良好等情，並無不能注意之情事，\r\n    竟疏未注意及此，因煞車不及，所騎乘機車頭碰撞前方等停\r\n    紅燈上訴人所騎乘普通重型機車車尾，致上訴人人車倒地後\r\n    ，受有傷害，堪認被上訴人對系爭車禍之發生應有過失，且\r\n    其過失與上訴人身體受傷有相當因果關係。則上訴人依前揭\r\n    規定請求被上訴人負損害賠償之責，自屬有據。茲就上訴人\r\n    請求部分，分述如下： \r\n㈠醫療費：\r\n  上訴人主張：除原審判決被上訴人應予賠償之2,435元（已確\r\n  定）外，被上訴人應再給付上訴人373,481元（其中285,555元\r\n  為原審所駁回，87,926元為上訴人於第二審所擴張），並提出\r\n  診斷證明書、醫療費用單據為證（見附民卷第15-27頁、第31-\r\n  107頁、原審卷一第103-126頁、第129頁、133頁、第141頁、\r\n  第363-421頁、本院卷第91-118頁），上訴人受傷後除有於兩\r\n  造所不爭執之福雅診所就診支出醫療費用及醫療物品計2,435\r\n  元外，固有於附表一、二所示之醫療院所就診並支出費用，然\r\n  其支出是否係屬必要而應由被上訴人負擔，被上訴人則有所爭\r\n  執，本院依序審酌如下：\r\n⒈原審駁回部分即附表一所示部分：\r\n　⑴同春堂診所部分：上訴人確有支出18,820元，而其中2,260元\r\n    部分為掛號費、健保部分負擔，依上訴人所提收據確載：其\r\n    他身體損傷而就醫，雖其收據夾雜記載胃及十二指腸疾病、\r\n    消化系統疾病、身體病況引起的失眠症、慢性鼻咽炎、支氣\r\n    管炎等（見附民卷第 35-39頁），惟其診斷證明書明確記載\r\n    ：病名為108年9月6日車禍挫傷上肢、下肢瘀傷腫痛等（見\r\n    附民卷第41頁），顯見此部分支出與本案車禍受傷有關之必\r\n    要支出，被上訴人應予賠償。是此部分上訴人得請求被上訴\r\n    人賠償；至於水藥費16,560元部分，非屬健保給付項目，而\r\n    該等藥水對上訴人所受傷勢有何療效，復未見上訴人有所說\r\n    明及舉證，顯難認其有必要，該部分為上訴人為自我保養調\r\n    理所為之支出，此部分所為支出取決於上訴人主觀意見，自\r\n    不宜歸由被上訴人負擔。是此部分上訴人得請求被上訴人賠\r\n    償之部分應為2,260元，其餘尚難准許。\r\n  ⑵臺中榮民醫院部分：上訴人確有支出12,685元，有收據可參\r\n    （見原審附民卷第57-85頁、原審卷一第 365-392頁），且\r\n    收據載明為復健等而就診，被上訴人徒以就診療項目復健有\r\n    重覆檢查之虞，抗辯應予剔除云云，自無可採。此部分上訴\r\n    人請求被上訴人賠償，於法有據。\r\n　⑶永康中醫診所部分：上訴人確有支出15,890元，有收據可參\r\n    （見附民卷第87-107頁、原審卷一第111-126頁、第403-421\r\n    頁），上訴人受傷需長期治療，其至永康中醫診所復健治療\r\n     ，難認不當，被上訴人徒以上訴人方於109年2月27日始至\r\n    永康中醫診所求診，抗辯其傷勢與事故並無關聯云云，尚無\r\n    可採，是上訴人請求被上訴人此部分之賠償，於法有據。\r\n　⑷以馬內利診所部分：\r\n　①附表一所列掛號費8,050元及109年1月14日支出200元、110年\r\n    2 月22日支出410元部分，上訴人確有支出8,660元（見原審\r\n    附民卷第 43-44頁、49-55頁、原審卷一第 105-110頁、393\r\n    -402頁），此部分被上訴人抗辯：上訴人於108年9月10日始\r\n    至以馬內利診所求診，距離事故發生時已隔4天，顯然與此\r\n    次事故並無關聯云云，惟上訴人受傷需長期治療，其至以馬\r\n    內利診所從事健保復健治療，難認不當，是上訴人請求被上\r\n    訴人賠償，於法有據。\r\n　②至於其他所列治療費、徒手治療費（就診日期參見如附表三\r\n    、四所示上訴人所陳報之日期），其中徒手治療欄所載治療\r\n    費用之2,700元、3,600元部分，為增生療法費用，部分3,60\r\n    0元費用為2次徒手治療的費用合併開立(單次1,800元)之費\r\n    用，附表二之15,000元為使用高濃度血小板做增生注射的費\r\n    用等情，為兩造所不爭執，並有以馬內利診所112年3月13 \r\n    日以馬復字第1120313001號函（見本卷531-532頁），在卷\r\n    可參。又附表一以馬內利診所欄部分編號1-23號所列之治療\r\n    費（即3,000元、3,500元、3,600元、3,700元等），審其繳\r\n    費單據（見附民第49-55頁、原審卷一第393-402頁）之記載\r\n    ，均與前述徒手治療費收據（見附民卷第43-44頁、原審卷\r\n    一第105-110頁、第397-402頁）之記載相同，是該等費用之\r\n    治療內容，亦屬徒手治療費用，應可認定。按上訴人受傷後\r\n    本得在健保給付之範圍內進行復健，且該等費用之部分負擔\r\n    ，自屬得請求被上訴人之賠償範圍。惟上訴人除健保給付之\r\n    復健外，額外自行付費請求徒手按摩治療部分，本非健保給\r\n    付項目，上訴人單憑己意密集自行僱人進行該徒手按摩，自\r\n    難認該等費用為必要治療費用，以馬內利診所函稱該等費用\r\n    為必要治療費用，尚無可採。又前述增生療法費用並非健保\r\n    給付項目，雖以馬內利診所函稱該等費用亦為必要治療費用\r\n    ，惟上訴人受傷後除有在以馬內利診所治療外，亦有於福雅\r\n    診所、臺中榮民醫院接受長期治療及復健，然福雅診所、臺\r\n    中榮民醫院均未有進行或建議從事增生療法，觀之該等治療\r\n    費用高昂，屬健保不為支付之項目，該等治療行為客觀已難\r\n    認絕對必要，端看個人意願及支付能力而定。且上訴人自11\r\n    0年3 月後密集上開增生療法，顯見上訴人急於取得療效之\r\n    心，期間更進行15,000元以上之高濃度血小板做增生注射，\r\n    該等治療一般是職業運動選手為不進行開刀治療以求早日得\r\n    再上場競技之治療方法，報章雜誌及網路早已流傳，該治療\r\n    方法並非每個人都適合，更要參考受傷程度、個人體質、個\r\n    人療效、注射後保養等，是上開治療方法非一般常規治療，\r\n    而是取決於上訴人個人意志之治療方式，顯難認其治療有必\r\n    要性，此部分上訴人依個人意志之花費與被上訴人之侵害無\r\n    相當因果關係，上訴人請求被上訴人賠償，應屬無據。\r\n　⑸中科學善物理治療所部分：　\r\n　  按中科學善物理治療所並非醫療院所，而上訴人未提出相關\r\n    醫療院所出具指定上訴人應於如附表五所示期日，至中科學\r\n    善物理治療所從事徒手按摩之醫囑，顯見此部分之物理治療\r\n    乃上訴人己意所為，並與其他醫療院所之治療重複，難認為\r\n    治療傷害過程之必要支出費用，是上訴人請求被上訴人賠償\r\n    其費用，於法無據。　\r\n　⑹基上，如附表一所列之費用，上訴人得再請求被上訴人賠償\r\n    之金額為39,495元（2,260元+12,685元+15,890元+8,660元\r\n    ），其餘請求即屬無據。\r\n  ⒉上訴人擴張部分即如附表二所示部分：\r\n　⑴臺中榮民醫院部分：\r\n　　依上訴人所提出之收據（見本院卷第 91-102頁），扣除編\r\n    號1、2、3、4、42、46、47之診斷證明書費及供申領保險用\r\n    之收據證明費用，屬於與治療無關之無益費用，上訴人不得\r\n    請求被上訴人賠償外，其他編號19、30、41、45、52號之治\r\n    療費用合計3,086元，均屬必要支出，上訴人擴張請求被上\r\n    訴人賠償，於法有據。  \r\n　⑵永康中醫診所部分：\r\n　　依上訴人所提出之收據（見本院卷第109-118頁），扣除編\r\n    號38、39、40之診斷證明書費，屬於與治療無關之無益費用\r\n    ，上訴人不得請求被上訴人賠償外，其他編號5-8、12-14、\r\n    16-17、22-23、26-29、33、37號之治療費用合計1,370元，\r\n    均屬必要支出，上訴人擴張請求被上訴人賠償，於法有據。\r\n      \r\n　⑶以馬內利診所部分： \r\n　　依上訴人所提出之收據（見本院卷第103-108頁）扣除編號9\r\n    、10、15、18、20、24-25、31、34-36、43、48-49、51號\r\n    之增生療法、徒手治療費用，屬於非必要治療之無益費用，\r\n    上訴人不得請求被上訴人賠償外，其他編號11、21、32、44\r\n    、50號之治療費用合計1,750元，均屬必要支出，上訴人擴\r\n    張請求被上訴人賠償，於法有據。\r\n　⑷基上，如附表二所列之費用，上訴人得擴張求被上訴人賠償\r\n    之金額為6,206元（3,086元+1,370元+1,750元），其餘請求\r\n    即屬無據。　　\r\n  ㈡關於勞動能力減損部分：\r\n　⒈關於勞動能力減少之比例：　 \r\n　  上訴人因系爭傷勢所受勞動能力之減損比例，前經臺大醫院\r\n    雲林分院於111年9月23日以「美國醫學會永久失能評估指引\r\n    第6版」及「美國加州永久失能評估準則2005年版」，依本\r\n    院所提供之過往就醫資料與醫院門診鑑定時所呈現之臨床症\r\n    狀及徵象，並將其工作經歷及事故時之年齡納入考量，經計\r\n    算可得其勞動能力減損之比例為10%。有該分院111年11月15\r\n    日臺大雲分資字第1111009314號函可按（見本院卷第429-43\r\n    0頁）。是本院認為上訴人勞動能力減損比例為10%，應可認\r\n    定。\r\n　⒉關於勞動能力減少之賠償金額：　　　　 \r\n　⑴按民法第193條第1項規定，不法侵害他人之身體或健康者，\r\n    對於被害人因此喪失或減少勞動能力，或增加生活上之需要\r\n    時，應負損害賠償責任，是被害人身體或健康受侵害，致喪\r\n    失或減少勞動能力，其本身即為損害，此因勞動能力減少所\r\n    生之損害，不以實際已發生者為限（最高法院93年度台上字\r\n    第1489號判決意旨參照）。被上訴人雖辯稱上訴人勞動能力\r\n    減少之損害賠償，應採實際所得喪失說云云，然上訴人既受\r\n    侵害致使勞動能力有所減損，客觀上即受有損害，其自得請\r\n    求被上訴人賠償，至於上訴人就其剩餘勞動能力事後可取得\r\n    多少報酬，並非所問。是上訴人就其喪失勞動能力部分，不\r\n    問其在原工作場所，可否依時間、經驗累積而取得比肇事時\r\n    所領得之更高薪資，並無礙上訴人受有損害之情事認定，自\r\n    應由被上訴人填補其喪失勞動能力之損害，始符公允。是上\r\n    訴人前述抗辯，並無可取。\r\n　⑵按被害人因身體健康被侵害而喪失勞動能力所受之損害，其\r\n    金額應就被害人受侵害前之身體健康狀態、教育程度、專門\r\n    技能、社會經驗等方面酌定之，不能以一時一地之工作收入\r\n    為準（最高法院63年台上字第1394號判決意旨參照）。經查\r\n    ，上訴人東海大學社會系畢業，於系爭車禍發生時為31歲，\r\n    任職於勞動部擔任辦事員，月薪資38,750元，有上訴人所提\r\n    出108年9月之入帳通知單（見本院卷第 289 頁）可參。而\r\n    今上訴人所提111年1月薪資入帳通知書，內載薪資為40,369\r\n    元（見本院卷第273頁)，顯見上訴人未因勞動能力減損而遭\r\n    原任職單位減薪，自無從依上訴人工作單位薪資之變化以計\r\n    算勞動能力減損之數額。按上訴人確受有損害，而其數額無\r\n    法證明，審諸勞動能力減損係屬抽象勞動能力之喪失，其損\r\n    害數額之計算標準，既無其他更為客觀標準可得參酌，本院\r\n    認依行政院公告之肇事當年最低基本工資作為計算基準，應\r\n    符合兩造間之利益。則上訴人於108年9月6日受傷時，其勞\r\n    動能力已受損減少10%，當年最低基本工資每月為23,100元\r\n    ，換算每年則為277,200元【計算式：23,100元 ×12=277,20\r\n    0元】。\r\n　⒊上訴人請求自其108年9月6日起，至其滿65歲之142年9月5日\r\n    止之勞動能力減損，又其勞動能力減少比例為10%，已如前\r\n    述。則按霍夫曼式計算法扣除中間利息（首期給付不扣除中\r\n    間利息）核計其得一次請求給付之金額，為559,456元【計\r\n    算方式如附件】。是上訴人得請求被上訴人給付勞動能力減\r\n    少之損害，為559,456元；逾此部分之請求，尚難准許。\r\n　㈢慰撫金部分：\r\n　　按慰撫金之賠償須以人格權遭遇侵害，使精神上受有痛苦為\r\n    必要，其核給之標準固與財產上損害之計算不同，然非不可\r\n    斟酌雙方身分資力與加害程度，及其他各種情形核定相當之\r\n    數額（最高法院51年台上字第223號判決意旨參照）。上訴\r\n    人因被上訴人之過失行為受傷，其精神及肉體上自受有痛苦\r\n    ，請求被上訴人賠償慰撫金，即屬有據。上訴人為東海大學\r\n    社會系畢業，於系爭車禍發生時為31歲，任職於勞動部擔任\r\n    辦事員，月薪資38,750元，已如前述，被上訴人於107年、1\r\n    08年度無薪資所得申報資料，其名下有土地 3筆、房屋1筆 \r\n    價值約430萬元左右，有財產調件明細表（見原審卷一，外\r\n    放）在卷可憑，被上訴人有撫養配偶和子女共2人等情，被\r\n    上訴人陳述在卷可按（見本院卷第 545頁）。爰衡酌兩造身\r\n    分、經濟狀況、資力、上訴人因系爭車禍所受傷勢影響其日\r\n    常生活之程度、系爭車禍發生迄今已近4年仍無法獲得相當\r\n    之賠償等一切情狀，認上訴人請求精神慰撫金以25萬元為適\r\n    當；逾此部分之請求，尚屬過高，無從准許。\r\n四、基上所述，上訴人除原審已確定之醫療費用2,435元，慰撫\r\n    金 25,000元外，就醫療費用尚得再請求被上訴人賠償醫療\r\n    費用45,701元（其中39,495元為原審請求未准許部分；及第\r\n    二審擴張請求部分為6,206元）；就勞動能力減少之損害部\r\n    分，得請求被上訴人賠償559,456元（第一審請求277,603元\r\n    ；其餘擴張請求281,853元）； 就慰撫金部分得再請求被上\r\n    訴人賠償225,000元（25萬元-25000元）。是上訴人上訴請\r\n    求被上訴人再給付542,098元（39,495元醫療費用、勞動能\r\n    力減少之損害部分277,603元、慰撫金部分225,000元），及\r\n    擴張請求被上訴人給付288,059元（醫療費用6,206元、勞動\r\n    能力減損281,853元），於法有據。\r\n五、損害之發生或擴大，被害人與有過失者，法院得減輕賠償金\r\n    額，或免除之，雖為民法第217條第1項所明定。惟本件車禍\r\n    之發生係因被上訴人自後追撞等停紅燈中之上訴人，上訴人\r\n    就本件車禍並無過失，上訴人既無過失，自不得減輕或免除\r\n    賠償金額。至於上訴人於醫囑休養期間從事諸如實彈射擊、\r\n    路跑、射箭、極限戰鬥拳及加強背部、肩部肌肉訓練、跳躍\r\n    及斜坡衝刺跑步之活動，進而影響或遲延其身體復原進程云\r\n    云，被上訴人並未舉證證明，該活動確有發生加劇傷勢之情\r\n    事，尚難遽以被上訴人單方抗辯即認上訴人有從事上開活動\r\n    並有加劇傷勢之事實存在。況上訴人已說明其有參加路跑活\r\n    動，惟上訴人主張該次路跑速度與一般日常步行速度相近，\r\n    與上肢活動較無關係，且其他運動亦僅是進行有助於受傷組\r\n    織修復及重建之適當活動等語，尚難遽認上訴人有過度負荷\r\n    造成二次傷害之情事存在。被上訴人抗辯上訴人有與有過失\r\n    之情事云云，自無可採 。\r\n六、按保險人依本法規定所為之保險給付，視為被保險人損害賠\r\n    償金額之一部分；被保險人受賠償請求時，得扣除之；強制\r\n    汽車責任保險法第32條定有明文。新光產物保險公司已賠付\r\n    上訴人強制汽車責任保險金140,926元，有上訴人所提出之\r\n    理賠證明（見本院卷第85-89頁），在卷可參，此部分金額\r\n    應自賠償數額中予以扣除。是上訴人上訴再請求被上訴人給\r\n    付部分542,098元於扣除140,926元，上訴人得再請求被上訴\r\n    人給付401,172元。\r\n七、綜上所述，上訴人得請求被上訴人賠償之金額，除原審確定\r\n    之醫療費用2,435元，慰撫金25,000元外，尚得上訴請求被\r\n    上訴人再給付401,172元，及擴張請求被上訴人給付288,059\r\n    元（醫療費用6,206元、勞動能力減損281,853元），是上訴\r\n    人依侵權行為之法律關係，上訴請求被上訴人再給付401,17\r\n    2元，及自110年5月29日（即110年5 月24 日民事準備四狀\r\n    繕本送達之翌日，見原審卷二第249頁送達回執）起，至清\r\n    償日止，按年息百分之五計算之利息；擴張請求被上訴人給\r\n    付288,059元，及其中6,206元自110年10 月15 日（即上訴\r\n    聲明狀送達翌日，見本院卷第第21頁，送達回證）起，其中\r\n    281,853元自111年5 月24 日（即擴張聲明㈢狀送達翌日，見\r\n    本院卷第381頁，111年5 月23日準備程序筆錄）起，均至清\r\n    償日止，按年息百分之五計算之利息，為有理由，應予准許\r\n    ；上訴人逾此部分之請求，為無理由，應予駁回。從而，㈠\r\n    原審駁回上訴人上開上訴應予准許部分，尚有未洽，上訴人\r\n    上訴意旨指摘原判決此部分不當，求予廢棄改判，為有理由\r\n    ，此部分應由本院廢棄改判如主文第2項所示；又原審就上\r\n    開不應准許部分，為上訴人敗訴之判決，並駁回其假執行之\r\n    聲請，核無違誤，上訴人上訴論旨指摘原判決此部分不當，\r\n    求予廢棄改判，為無理由，應駁回此部分之上訴；㈡上訴人\r\n    於擴張請求部分，則部分有理由，爰諭知如主文第3項所示\r\n    ；惟逾此部分則無理由，應予駁回。\r\n八、未按，本件命被上訴人給付金額及上訴人敗訴部分均未逾15\r\n    0萬元，兩造均不得上訴，本判決於宣示判決後即已確定，\r\n    故本院無庸另依職權宣告上訴人得假執行或被上訴人得供相\r\n    當擔保免為假執行，附此敘明。\r\n伍、本件事證已臻明確，兩造其餘訴訟資料及攻擊防禦方法，經\r\n     本院審酌後，認與判決結果尚不生影響，無逐一論述之必\r\n    要 ，附此敘明。\r\n陸、據上論結，上訴人之上訴及擴張之訴均為一部有理由、一部\r\n    無理由，依民事訴訟法第436條之1第3項、第450條、第449\r\n    條第1項、第79條、第463條，判決如主文。\r\n中　　華　　民　　國　　112 　年　　8 　　月　　25　　日\r\n               民事第三庭   審判長法  官　陳宗賢\r\n\r\n　　                              法  官  林秉暉\r\n　　　　　　　　　　　　　　　　　\r\n　　　　　　　　　　　　　　　　　法  官　王金洲　　　\r\n以上正本係照原本作成。　　　　　　　　　　　　　　　　　\r\n本判決不得上訴。\r\n中　　華　　民　　國　　112 　年　　8 　　月　　25　　日\r\n                                  書記官 林奕珍　\r\n附件：\r\n依霍夫曼式計算法扣除中間利息（首期給付不扣除中間利息）核\r\n計其金額為新臺幣559,456元【計算方式為：27,720×19.0000000\r\n0+(27,720×0.00000000)×(20.00000000-00.00000000)=559,456.\r\n0000000000。其中19.00000000為年別單利5%第33年霍夫曼累計\r\n係數，20.00000000為年別單利5%第34年霍夫曼累計係數，0.000\r\n00000為未滿一年部分折算年數之比例(364/365=0.00000000)。\r\n採四捨五入，元以下進位】。","JPDF":"https://data.judicial.gov.tw/opendl/JDocFile/TCDV/110%2c%e7%b0%a1%e4%b8%8a%2c403%2c20230825%2c1.pdf"}